djtools/__init__.py
djtools/__main__.py
djtools/version.py
djtools/collection/__init__.py
djtools/collection/base_collection.py
djtools/collection/base_playlist.py
djtools/collection/base_track.py
djtools/collection/config.py
djtools/collection/copy_playlists.py
djtools/collection/helpers.py
djtools/collection/platform_registry.py
djtools/collection/playlist_builder.py
djtools/collection/playlist_filters.py
djtools/collection/rekordbox_collection.py
djtools/collection/rekordbox_playlist.py
djtools/collection/rekordbox_track.py
djtools/collection/shuffle_playlists.py
djtools/configs/__init__.py
djtools/configs/cli_args.py
djtools/configs/config.py
djtools/configs/config_formatter.py
djtools/configs/helpers.py
djtools/logs/__init__.py
djtools/spotify/__init__.py
djtools/spotify/config.py
djtools/spotify/helpers.py
djtools/spotify/playlist_builder.py
djtools/sync/__init__.py
djtools/sync/config.py
djtools/sync/helpers.py
djtools/sync/sync_operations.py
djtools/utils/__init__.py
djtools/utils/check_tracks.py
djtools/utils/config.py
djtools/utils/helpers.py
djtools/utils/normalize_audio.py
djtools/utils/process_recording.py
djtools/utils/url_download.py
djtools-2.9.0.dist-info/licenses/LICENSE
djtools-2.9.0.dist-info/METADATA
djtools-2.9.0.dist-info/WHEEL
djtools-2.9.0.dist-info/entry_points.txt
djtools-2.9.0.dist-info/top_level.txt
djtools-2.9.0.dist-info/RECORD
